abalone/__init__.py
abalone/abstract_player.py
abalone/enums.py
abalone/game.py
abalone/human_player.py
abalone/random_player.py
abalone/run_game.py
abalone/utils.py
abalone_boai-1.0.0.dist-info/LICENSE.md
abalone_boai-1.0.0.dist-info/METADATA
abalone_boai-1.0.0.dist-info/WHEEL
abalone_boai-1.0.0.dist-info/top_level.txt
abalone_boai-1.0.0.dist-info/RECORD
